LICENSE
MANIFEST.in
README.rst
setup.py
batch_select/__init__.py
batch_select/models.py
batch_select/replay.py
batch_select/tests.py
django_batch_select.egg-info/PKG-INFO
django_batch_select.egg-info/SOURCES.txt
django_batch_select.egg-info/dependency_links.txt
django_batch_select.egg-info/top_level.txt
django_batch_select.egg-info/zip-safe
tests/run_tests.sh
tests/test_settings.py