Metadata-Version: 1.1
Name: django-batch-select
Version: 0.2.4
Summary: batch select many-to-many and one-to-many fields (to help avoid n+1 query problem)
Home-page: http://github.com/lilspikey/django-batch-select/
Author: John Montgomery
Author-email: john@littlespikeyland.com
License: BSD
Download-URL: http://github.com/lilspikey/django-batch-select/downloads
Platform: UNKNOWN
Classifier: Development Status :: 4 - Beta
Classifier: Environment :: Web Environment
Classifier: Framework :: Django
Classifier: Intended Audience :: Developers
Classifier: License :: OSI Approved :: BSD License
Classifier: Operating System :: OS Independent
Classifier: Programming Language :: Python
Classifier: Topic :: Software Development :: Libraries :: Python Modules
